ospx/__init__.py
ospx/component.py
ospx/connection.py
ospx/connector.py
ospx/graph.py
ospx/importer.py
ospx/ospCaseBuilder.py
ospx/ospSimulationCase.py
ospx/py.typed
ospx/simulation.py
ospx/system.py
ospx/cli/__init__.py
ospx/cli/importSystemStructure.py
ospx/cli/ospCaseBuilder.py
ospx/fmi/__init__.py
ospx/fmi/experiment.py
ospx/fmi/fmu.py
ospx/fmi/unit.py
ospx/fmi/variable.py
ospx/utils/__init__.py
ospx/utils/dateTime.py
ospx/utils/dict.py
ospx/utils/logging.py
ospx/utils/plotting.py
ospx/utils/zip.py
ospx/watch/__init__.py
ospx/watch/watchCosim.py
ospx/watch/cli/__init__.py
ospx/watch/cli/watchCosim.py
ospx-0.3.2.dist-info/METADATA
ospx-0.3.2.dist-info/WHEEL
ospx-0.3.2.dist-info/entry_points.txt
ospx-0.3.2.dist-info/licenses/LICENSE
ospx-0.3.2.dist-info/RECORD
