Metadata-Version: 2.4
Name: ospx
Version: 0.3.2
Summary: Extension package to farn, adding support to build OSP simulation cases using FMUs.
Project-URL: Homepage, https://github.com/dnv-opensource/ospx
Project-URL: Documentation, https://dnv-opensource.github.io/ospx/README.html
Project-URL: Repository, https://github.com/dnv-opensource/ospx.git
Project-URL: Issues, https://github.com/dnv-opensource/ospx/issues
Project-URL: Changelog, https://github.com/dnv-opensource/ospx/blob/main/CHANGELOG.md
Author-email: Frank Lumpitzsch <frank.lumpitzsch@dnv.com>, Claas Rostock <claas.rostock@dnv.com>, Seunghyeon Yoo <seunghyeon.yoo@dnv.com>
Maintainer-email: Claas Rostock <claas.rostock@dnv.com>
License: MIT License
License-File: LICENSE
Keywords: OSP,farn,fmi
Classifier: Development Status :: 4 - Beta
Classifier: Environment :: Console
Classifier: Intended Audience :: Developers
Classifier: Intended Audience :: Science/Research
Classifier: License :: OSI Approved :: MIT License
Classifier: Operating System :: MacOS
Classifier: Operating System :: Microsoft :: Windows
Classifier: Operating System :: POSIX :: Linux
Classifier: Programming Language :: Python :: 3.11
Classifier: Programming Language :: Python :: 3.12
Classifier: Programming Language :: Python :: 3.13
Classifier: Programming Language :: Python :: 3.14
Classifier: Topic :: Scientific/Engineering
Classifier: Topic :: Software Development :: Libraries :: Python Modules
Requires-Python: <3.15,>=3.11
Requires-Dist: dictio>=0.4.2
Requires-Dist: graphviz>=0.20
Requires-Dist: lxml>=6.0
Requires-Dist: matplotlib>=3.10
Requires-Dist: numpy>=2.3
Requires-Dist: pandas>=2.3
